django_excel_base/__init__.py
django_excel_base/compat.py
django_excel_base/excel.py
django_excel_base-1.0.7.dist-info/METADATA
django_excel_base-1.0.7.dist-info/WHEEL
django_excel_base-1.0.7.dist-info/top_level.txt
django_excel_base-1.0.7.dist-info/RECORD
